csdt_stl_tools/__init__.py
csdt_stl_tools/cwrapped.c
csdt_stl_tools/cwrapped.cpython-37m-darwin.so
csdt_stl_tools/cwrapped.pyx
csdt_stl_tools/image2stl.py
csdt_stl_tools/numpy2stl.py
csdt_stl_tools/text2png.py
csdt_stl_tools-0.5.4.dist-info/LICENSE.txt
csdt_stl_tools-0.5.4.dist-info/METADATA
csdt_stl_tools-0.5.4.dist-info/WHEEL
csdt_stl_tools-0.5.4.dist-info/entry_points.txt
csdt_stl_tools-0.5.4.dist-info/top_level.txt
csdt_stl_tools-0.5.4.dist-info/RECORD
