Metadata-Version: 2.1
Name: csdt-stl-tools
Version: 0.5.4
Summary: Generate STL files from numpy arrays and text (based on thearn/stl_tools)
Home-page: https://github.com/CSDTs/csdt_stl_tools
Author: Andrew Hunn
Author-email: ahunn@umich.edu
License: Apache 2.0
Platform: UNKNOWN
Requires-Dist: numpy (<1.24)
Requires-Dist: scipy
Requires-Dist: matplotlib
